SerializableSimpy/MPI_core.py
SerializableSimpy/MPI_utils.py
SerializableSimpy/MP_core.py
SerializableSimpy/MP_utils.py
SerializableSimpy/__init__.py
SerializableSimpy/core.py
SerializableSimpy/monitor_event_tracing.py
serializable_simpy-0.0.3.dist-info/licenses/LICENSE
serializable_simpy-0.0.3.dist-info/METADATA
serializable_simpy-0.0.3.dist-info/WHEEL
serializable_simpy-0.0.3.dist-info/top_level.txt
serializable_simpy-0.0.3.dist-info/RECORD
