Metadata-Version: 2.4
Name: serializable_simpy
Version: 0.0.3
Summary: Simpy with 
Home-page: https://gitlab.com/uniluxembourg/hpc/research/cadom/serializable-simpy/-/issues
Author: Pierrick Pochelu
Author-email: Pierrick Pochelu <pierrick.pochelu@gmail.com>
License: Apache-2.0
Project-URL: Homepage, https://gitlab.com/uniluxembourg/hpc/research/cadom/serializable-simpy
Project-URL: Bug Tracker, https://gitlab.com/uniluxembourg/hpc/research/cadom/serializable-simpy/-/issues
Classifier: Programming Language :: Python :: 3
Classifier: Operating System :: OS Independent
Requires-Python: >=3.8
License-File: LICENSE
Dynamic: author
Dynamic: home-page
Dynamic: license-file
Dynamic: requires-python
